powerline_gitstatus/__init__.py
powerline_gitstatus/segments.py
powerline_gitstatus-1.3.3.dist-info/LICENSE
powerline_gitstatus-1.3.3.dist-info/METADATA
powerline_gitstatus-1.3.3.dist-info/WHEEL
powerline_gitstatus-1.3.3.dist-info/top_level.txt
powerline_gitstatus-1.3.3.dist-info/RECORD
